{
  "$schema": "https://mintlify.com/docs.json",
  "theme": "mint",
  "name": "documentation | snipin.ai",
  "colors": {
    "primary": "#000000",
    "light": "#ffffff",
    "dark": "#ffffff"
  },
  "favicon": "/favicon.svg",
  "navigation": {
    "groups": [
      {
        "group": "Getting started",
        "pages": [
          "getting-started/introduction",
          "getting-started/create-account",
          "getting-started/create-project",
          "getting-started/publish-content",
          "getting-started/share-snippet",
          "getting-started/analytics-insight",
          "getting-started/settings",
          "getting-started/reprocessing"
          
        ]
      }
    ]
  },
  "logo": {
    "light": "/logo/light.png",
    "dark": "/logo/dark.png"
  }
}